README
setup.py
quickSms.egg-info/PKG-INFO
quickSms.egg-info/SOURCES.txt
quickSms.egg-info/dependency_links.txt
quickSms.egg-info/top_level.txt
smsEngine/__init__.py
smsEngine/contentPerser.py
smsEngine/htmlPaginationGrabber.py
smsEngine/one6tiby2.py
smsEngine/sms.py
smsEngine/svnwayssms.py
smsEngine/way2sms.py