Metadata-Version: 1.1
Name: quickSms
Version: 1.1
Summary: Easy way to send an sms from CLI using 160by2/way2sms
Home-page: http://github.com/dipankar08/craZyeXp/
Author: Dipankar Dutta
Author-email: dutta.dipankar08@gmail.com
License: BSD
Keywords: sms 160by2 way2sms message chat mobile
Platform: UNKNOWN
Classifier: Development Status :: 3 - Alpha
Classifier: Topic :: Utilities
Classifier: License :: OSI Approved :: BSD License
